katatachi/__init__.py
katatachi/app.py
katatachi/version.py
katatachi/blueprints/__init__.py
katatachi/blueprints/mod_view_blueprint.py
katatachi/blueprints/pipeline_blueprint.py
katatachi/blueprints/worker_blueprint.py
katatachi/content/__init__.py
katatachi/content/content_store.py
katatachi/contrib/__init__.py
katatachi/contrib/api/__init__.py
katatachi/contrib/api/timeline.py
katatachi/contrib/mod_view/__init__.py
katatachi/contrib/mod_view/echo.py
katatachi/contrib/mod_view/update_one_button.py
katatachi/contrib/worker/__init__.py
katatachi/contrib/worker/example.py
katatachi/contrib/worker/twitter_media.py
katatachi/contrib/worker/twitter_media_scraper.py
katatachi/contrib/worker/utils.py
katatachi/interface/__init__.py
katatachi/interface/api/__init__.py
katatachi/interface/api/api_blueprint_factory.py
katatachi/interface/mod_view/__init__.py
katatachi/interface/mod_view/column.py
katatachi/interface/mod_view/column_render.py
katatachi/interface/worker/__init__.py
katatachi/interface/worker/metadata_store.py
katatachi/interface/worker/work_context.py
katatachi/interface/worker/worker.py
katatachi/mod_view/__init__.py
katatachi/mod_view/mod_view_query.py
katatachi/mod_view/mod_view_renderer.py
katatachi/mod_view/mod_view_store.py
katatachi/pipeline/__init__.py
katatachi/pipeline/configure_pipeline.py
katatachi/pipeline/pipeline.py
katatachi/pipeline/pipeline_mod_view.py
katatachi/pipeline/pipeline_source.py
katatachi/pipeline/pipeline_state.py
katatachi/pipeline/pipeline_worker.py
katatachi/pipeline/pipeline_worker_class.py
katatachi/pipeline/state_key.py
katatachi/pipeline/state_update.py
katatachi/reconciler/__init__.py
katatachi/reconciler/reconciler.py
katatachi/reconciler/start_reconciler_blocking.py
katatachi/utils/__init__.py
katatachi/utils/database_migration.py
katatachi/utils/datetime.py
katatachi/utils/env.py
katatachi/utils/gcd.py
katatachi/web/asset-manifest.json
katatachi/web/favicon.ico
katatachi/web/index.html
katatachi/web/manifest.json
katatachi-1.1.2.dist-info/LICENSE
katatachi-1.1.2.dist-info/METADATA
katatachi-1.1.2.dist-info/WHEEL
katatachi-1.1.2.dist-info/top_level.txt
katatachi-1.1.2.dist-info/RECORD
