Metadata-Version: 2.1
Name: katatachi
Version: 1.1.2
Summary: A Python framework to build web scraping applications.
Home-page: https://github.com/k-t-corp/katatachi
Author: KTachibanaM
Author-email: whj19931115@gmail.com
License-File: LICENSE
Requires-Dist: flask (==2.1.2)
Requires-Dist: pika (==1.0.1)
Requires-Dist: pymongo (==3.12.2)
Requires-Dist: flask-cors (==3.0.10)
Requires-Dist: flask-jwt-extended (==4.4.0)
Requires-Dist: dnspython (==1.16.0)
Requires-Dist: jsonschema (==3.0.1)
Requires-Dist: apscheduler (==3.6.0)
Requires-Dist: sentry-sdk (==1.5.1)
Requires-Dist: redis (==3.5.3)
Requires-Dist: tzlocal (<3.0)
Requires-Dist: Flask-Limiter[redis] (==2.6.2)
Requires-Dist: celery (==5.2.7)
Requires-Dist: oauthlib (==3.1.0)
Requires-Dist: requests (<3.0.0)
Requires-Dist: python-twitter (==3.5)
